setup.py
pyChocolate/Chocolate.py
pyChocolate/__init__.py
pyChocolate.egg-info/PKG-INFO
pyChocolate.egg-info/SOURCES.txt
pyChocolate.egg-info/dependency_links.txt
pyChocolate.egg-info/requires.txt
pyChocolate.egg-info/top_level.txt