Metadata-Version: 1.2
Name: pyChocolate
Version: 0.0.2.2
Summary: debugger and logger for python
Home-page: UNKNOWN
Author: Mevlüt Kaan Karakoç
Author-email: karakockaan326@gmail.com
License: MIT
Project-URL: Github, https://www.github.com/kaankarakoc42/pyChocolate
Keywords: debugger-logger
Platform: UNKNOWN
Classifier: Development Status :: 5 - Production/Stable
Classifier: Intended Audience :: Education
Classifier: Operating System :: Microsoft :: Windows :: Windows 10
Classifier: License :: OSI Approved :: MIT License
Classifier: Programming Language :: Python :: 3
